004_FSM/002_1010_Sequence_detector/01_non_overlapping/1010_sequence_nonoverlapping.v
module sequence_1010(
input clk,
input rst,
input x,
output reg y
);
reg [1:0]state,next_state;
parameter s0=2'b00,
	s1=2'b01,
	s2=2'b10,
	s3=2'b11;
always @(posedge clk or posedge rst)begin
if (rst)
	state <=s0;
else
	state<=next_state;
end
always @(*)begin
	case(state)
		s0:next_state = x? s1:s0;
		s1:next_state = x? s1:s2;
		s2:next_state = x? s3:s0;
		s3:next_state = x? s1:s0;
		default:next_state = s0;
endcase
end
always @(*) begin
    y = (state == s3 && (~x));
end
endmodule

004_FSM/002_1010_Sequence_detector/01_non_overlapping/1010_sequence_nonoverlapping_tb.v
module sequence_1010_tb;
reg clk,rst,x;
wire y;
sequence_1010 uut(
.clk(clk),
.rst(rst),
.x(x),
.y(y)
);
always #5 clk = ~clk;
initial begin
$dumpfile("1010_sequence.vcd");
$dumpvars(0,sequence_1010_tb);
clk = 0;
rst =1;
#10 rst = 0;
x = 1;#10;
x = 0;#10;
x = 1;#10;
x = 0;#10;
x = 1;#10;
x = 0;#10;
$finish;
end
endmodule

004_FSM/002_1010_Sequence_detector/01_non_overlapping/1010_sequence.vcd
$date
	Wed Jun 17 14:56:10 2026
$end
$version
	Icarus Verilog
$end
$timescale
	1s
$end
$scope module sequence_1010_tb $end
$var wire 1 ! y $end
$var reg 1 " clk $end
$var reg 1 # rst $end
$var reg 1 $ x $end
$scope module uut $end
$var wire 1 " clk $end
$var wire 1 # rst $end
$var wire 1 $ x $end
$var parameter 2 % s0 $end
$var parameter 2 & s1 $end
$var parameter 2 ' s2 $end
$var parameter 2 ( s3 $end
$var reg 2 ) next_state [1:0] $end
$var reg 2 * state [1:0] $end
$var reg 1 ! y $end
$upscope $end
$upscope $end
$enddefinitions $end
$comment Show the parameter values. $end
$dumpall
b11 (
b10 '
b1 &
b0 %
$end
#0
$dumpvars
b0 *
b0x )
x$
1#
0"
0!
$end
#5
1"
#10
b1 )
0"
1$
0#
#15
b1 *
1"
#20
b10 )
0"
0$
#25
b0 )
b10 *
1"
#30
b11 )
0"
1$
#35
b1 )
b11 *
1"
#40
b0 )
1!
0"
0$
#45
0!
b0 *
1"
#50
b1 )
0"
1$
#55
b1 *
1"
#60
b10 )
0"
0$
#65
b0 )
b10 *
1"
