002_Combinational_Circuits/007_Mux_8to1/mux_8to1.v
module mux_8to1(
input i0,i1,i2,i3,i4,i5,i6,i7,
input [2:0] sel,
output y
);
assign y = (sel == 3'b000) ? i0 :
(sel == 3'b001) ? i1 :
(sel == 3'b010) ? i2 :
(sel == 3'b011) ? i3 :
(sel == 3'b100) ? i4 :
(sel == 3'b101) ? i5 :
(sel == 3'b110) ? i6 :
i7;
endmodule

002_Combinational_Circuits/007_Mux_8to1/mux_8to1_tb.v
`timescale 1ns/1ps

module mux_8to1_tb;

reg i0, i1, i2, i3, i4, i5, i6, i7;
reg [2:0] sel;
wire y;

mux_8to1 uut (
    .i0(i0), .i1(i1), .i2(i2), .i3(i3),
    .i4(i4), .i5(i5), .i6(i6), .i7(i7),
    .sel(sel),
    .y(y)
);

initial begin
    $dumpfile("mux_8to1.vcd");
    $dumpvars(0, mux_8to1_tb);

    i0=0; i1=1; i2=0; i3=1;
    i4=0; i5=1; i6=0; i7=1;

    sel=3'b000; #10;
    sel=3'b001; #10;
    sel=3'b010; #10;
    sel=3'b011; #10;
    sel=3'b100; #10;
    sel=3'b101; #10;
    sel=3'b110; #10;
    sel=3'b111; #10;

    $finish;
end

endmodule

002_Combinational_Circuits/007_Mux_8to1/mux_8to1.vcd
$date
	Tue Jun  9 10:24:22 2026
$end
$version
	Icarus Verilog
$end
$timescale
	1ps
$end
$scope module mux_8to1_tb $end
$var wire 1 ! y $end
$var reg 1 " i0 $end
$var reg 1 # i1 $end
$var reg 1 $ i2 $end
$var reg 1 % i3 $end
$var reg 1 & i4 $end
$var reg 1 ' i5 $end
$var reg 1 ( i6 $end
$var reg 1 ) i7 $end
$var reg 3 * sel [2:0] $end
$scope module uut $end
$var wire 1 " i0 $end
$var wire 1 # i1 $end
$var wire 1 $ i2 $end
$var wire 1 % i3 $end
$var wire 1 & i4 $end
$var wire 1 ' i5 $end
$var wire 1 ( i6 $end
$var wire 1 ) i7 $end
$var wire 3 + sel [2:0] $end
$var wire 1 ! y $end
$upscope $end
$upscope $end
$enddefinitions $end
$comment Show the parameter values. $end
$dumpall
$end
#0
$dumpvars
b0 +
b0 *
1)
0(
1'
0&
1%
0$
1#
0"
0!
$end
#10000
1!
b1 *
b1 +
#20000
0!
b10 *
b10 +
#30000
1!
b11 *
b11 +
#40000
0!
b100 *
b100 +
#50000
1!
b101 *
b101 +
#60000
0!
b110 *
b110 +
#70000
1!
b111 *
b111 +
