004_FSM/003_0110_Sequence_detetctor/01_non-overlapping/0110_nonoverlap_moore.v
module non_overlap_0110(
	input clk,
	input rst,
	input x,
	output reg y
);
reg [2:0]state,next_state;
parameter s0 = 3'b000,
	s1 = 3'b001,
	s2 = 3'b010,
	s3 = 3'b011,
	s4 = 3'b100;
always @(posedge clk or posedge rst)begin
	if(rst)
		state<=s0;
	else
		state <= next_state;
end
always @(*)begin
	case(state)
		s0:next_state=x?s0:s1;
		s1:next_state=x?s2:s1;
		s2:next_state=x?s3:s1;
		s3:next_state=x?s0:s4;
		s4:next_state=s0;
		default:next_state = s0;
	endcase
end
always @(*) y = (state == s4);
endmodule

004_FSM/003_0110_Sequence_detetctor/01_non-overlapping/0110_nonoverlap_tb.v
module non_overlap_0110_tb;
reg clk,rst,x;
wire y;
non_overlap_0110 uut(
.clk(clk),
.rst(rst),
.x(x),
.y(y)
);
always #5 clk = ~clk;
initial begin
$dumpfile("0110_non_overlap.vcd");
$dumpvars(0,non_overlap_0110_tb);
clk =0;
rst = 1;
x =0;
#10 rst =0;
x=0;#10;
x=1;#10;
x=1;#10;
x=0;#10;
x=1;#10;
x=1;#10;
x=0;#10;
x=0;#10;
$finish;
end
endmodule

004_FSM/003_0110_Sequence_detetctor/01_non-overlapping/0110_non_overlap.vcd
$date
	Thu Jun 18 12:06:04 2026
$end
$version
	Icarus Verilog
$end
$timescale
	1s
$end
$scope module non_overlap_0110_tb $end
$var wire 1 ! y $end
$var reg 1 " clk $end
$var reg 1 # rst $end
$var reg 1 $ x $end
$scope module uut $end
$var wire 1 " clk $end
$var wire 1 # rst $end
$var wire 1 $ x $end
$var parameter 3 % s0 $end
$var parameter 3 & s1 $end
$var parameter 3 ' s2 $end
$var parameter 3 ( s3 $end
$var parameter 3 ) s4 $end
$var reg 3 * next_state [2:0] $end
$var reg 3 + state [2:0] $end
$var reg 1 ! y $end
$upscope $end
$upscope $end
$enddefinitions $end
$comment Show the parameter values. $end
$dumpall
b100 )
b11 (
b10 '
b1 &
b0 %
$end
#0
$dumpvars
b0 +
b1 *
0$
1#
0"
0!
$end
#5
1"
#10
0"
0#
#15
b1 +
1"
#20
b10 *
0"
1$
#25
b11 *
b10 +
1"
#30
0"
#35
b0 *
b11 +
1"
#40
b100 *
0"
0$
#45
1!
b0 *
b100 +
1"
#50
0"
1$
#55
0!
b0 +
1"
#60
0"
#65
1"
#70
b1 *
0"
0$
#75
b1 +
1"
