003_Sequential_Circuits/005_sr_flipflop/sr_flipflop.v
module sr_ff(input clk,s,r,output reg q ,output qn);
assign qn = ~q;
always @(posedge clk) begin
case({s,r})
2'b00:;
2'b01:q<=1'b0;
2'b10:q<=1'b1;
2'b11:q<=1'bx;
endcase
end
endmodule

003_Sequential_Circuits/005_sr_flipflop/sr_flipflop_tb.v
module sr_ff_tb;
reg s,r,clk;
wire q,qn;
sr_ff uut(
.clk(clk),
.s(s),
.r(r),
.q(q),
.qn(qn)
);
always #5 clk = ~clk;
initial begin
clk=0;
$dumpfile("sr_flipflop.vcd");
$dumpvars(0,sr_ff_tb);
s=0;r=0;#10;
s=0;r=1;#10;
s=0;r=0;#10;
s=1;r=0;#10;
s=0;r=0;#10;
s=1;r=1;#10;
$finish;
end
endmodule

003_Sequential_Circuits/005_sr_flipflop/sr_flipflop.vcd
$date
	Tue Jun 16 15:59:59 2026
$end
$version
	Icarus Verilog
$end
$timescale
	1s
$end
$scope module sr_ff_tb $end
$var wire 1 ! qn $end
$var wire 1 " q $end
$var reg 1 # clk $end
$var reg 1 $ r $end
$var reg 1 % s $end
$scope module uut $end
$var wire 1 # clk $end
$var wire 1 ! qn $end
$var wire 1 $ r $end
$var wire 1 % s $end
$var reg 1 " q $end
$upscope $end
$upscope $end
$enddefinitions $end
$comment Show the parameter values. $end
$dumpall
$end
#0
$dumpvars
0%
0$
0#
x"
x!
$end
#5
1#
#10
0#
1$
#15
1!
0"
1#
#20
0#
0$
#25
1#
#30
0#
1%
#35
0!
1"
1#
#40
0#
0%
#45
1#
#50
0#
1$
1%
#55
x!
x"
1#
