004_FSM/001_serial_2s_complementer/serial_2s_complementer.v
module twos_complementer(
	input clk,
	input rst,
	input x,
	output reg y
);
parameter A = 1'b0,
B = 1'b1;
reg state,next_state;
always @(posedge clk or posedge rst)begin
	if(rst)
		state<=A;
	else
		state <= next_state;
	end
always @(*) begin
case(state)
A: begin
if(x)
next_state = B;
else
next_state = A;
end
B:begin
next_state = B;
end
default:
next_state = A;
endcase
end
always @(*) begin
case(state)
A:y =x;
B:y=~x;
default: y =1'b0;
endcase
end
endmodule

004_FSM/001_serial_2s_complementer/serial_2s_complementer_tb.v
module twos_complementer_tb;
reg clk,rst,x;
wire y;
twos_complementer uut(
.x(x),
.clk(clk),
.rst(rst),
.y(y)
);
always #5 clk = ~clk;
initial begin
$dumpfile("twos_complementor.vcd");
$dumpvars(0,twos_complementer_tb);
clk=0;
rst=0;
x=0;#10;
x=0;#10;
x=0;#10;
x=1;#10;
x=0;#10;
x=1;#10;
x=0;#10;
x=1;#10;
x=1;#10;
x=0;#10;
x=1;#10;
x=0;#10;
$finish;
end
endmodule

004_FSM/001_serial_2s_complementer/twos_complementor.vcd
$date
	Wed Jun 17 10:16:34 2026
$end
$version
	Icarus Verilog
$end
$timescale
	1s
$end
$scope module twos_complementer_tb $end
$var wire 1 ! y $end
$var reg 1 " clk $end
$var reg 1 # rst $end
$var reg 1 $ x $end
$scope module uut $end
$var wire 1 " clk $end
$var wire 1 # rst $end
$var wire 1 $ x $end
$var parameter 1 % A $end
$var parameter 1 & B $end
$var reg 1 ' next_state $end
$var reg 1 ( state $end
$var reg 1 ! y $end
$upscope $end
$upscope $end
$enddefinitions $end
$comment Show the parameter values. $end
$dumpall
1&
0%
$end
#0
$dumpvars
x(
0'
0$
0#
0"
0!
$end
#5
0(
1"
#10
0"
#15
1"
#20
0"
#25
1"
#30
1!
1'
0"
1$
#35
0!
1(
1"
#40
1!
0"
0$
#45
1"
#50
0!
0"
1$
#55
1"
#60
1!
0"
0$
#65
1"
#70
0!
0"
1$
#75
1"
#80
0"
#85
1"
#90
1!
0"
0$
#95
1"
#100
0!
0"
1$
#105
1"
#110
1!
0"
0$
