002_Combinational_Circuits/004_Full_Subtractor/full_subtractor.v
module full_subtractor(input a,b,bi,output d,bo);
assign d = a^b^bi;
assign bo = ~a&bi | ~a&b | b&bi;
endmodule

002_Combinational_Circuits/004_Full_Subtractor/full_subtractor_tb.v
`timescale 1ns/1ps
module full_subtractor_tb;
reg a,b,bi;
wire bo,d;
full_subtractor uut(
.a(a),
.b(b),
.bi(bi),
.bo(bo),
.d(d)
);
initial begin
$dumpfile("full_subtractor.vcd");
$dumpvars(0,full_subtractor_tb);
a=0;b=0;bi=0;#10;
a=0;b=0;bi=1;#10;
a=0;b=1;bi=0;#10;
a=0;b=1;bi=1;#10;
a=1;b=0;bi=0;#10;
a=1;b=0;bi=1;#10;
a=1;b=1;bi=0;#10;
a=1;b=1;bi=1;#10;
$finish;
end
endmodule

002_Combinational_Circuits/004_Full_Subtractor/full_subtractor.vcd
$date
	Tue Jun  9 08:59:23 2026
$end
$version
	Icarus Verilog
$end
$timescale
	1ps
$end
$scope module full_subtractor_tb $end
$var wire 1 ! d $end
$var wire 1 " bo $end
$var reg 1 # a $end
$var reg 1 $ b $end
$var reg 1 % bi $end
$scope module uut $end
$var wire 1 # a $end
$var wire 1 $ b $end
$var wire 1 % bi $end
$var wire 1 " bo $end
$var wire 1 ! d $end
$upscope $end
$upscope $end
$enddefinitions $end
$comment Show the parameter values. $end
$dumpall
$end
#0
$dumpvars
0%
0$
0#
0"
0!
$end
#10000
1"
1!
1%
#20000
0%
1$
#30000
0!
1%
#40000
0"
1!
0%
0$
1#
#50000
0!
1%
#60000
0%
1$
#70000
1"
1!
1%
