002_Combinational_Circuits/006_2to1_mux/2to1_mux.v
module mux_2to1(input a,b,sel,output y);
assign y = sel ? a:b;
endmodule

002_Combinational_Circuits/006_2to1_mux/2to1_mux_tb.v
`timescale 1ns/1ps

module mux_2to1_tb;

reg a, b, sel;
wire y;

mux_2to1 uut (
    .a(a),
    .b(b),
    .sel(sel),
    .y(y)
);

initial begin
    $dumpfile("mux_2to1.vcd");
    $dumpvars(0, mux_2to1_tb);

    a=0; b=0; sel=0; #10;
    a=0; b=1; sel=0; #10;
    a=1; b=0; sel=0; #10;
    a=1; b=1; sel=0; #10;

    a=0; b=0; sel=1; #10;
    a=0; b=1; sel=1; #10;
    a=1; b=0; sel=1; #10;
    a=1; b=1; sel=1; #10;

    $finish;
end

endmodule

002_Combinational_Circuits/006_2to1_mux/mux_2to1.vcd
$date
	Tue Jun  9 09:58:03 2026
$end
$version
	Icarus Verilog
$end
$timescale
	1ps
$end
$scope module mux_2to1_tb $end
$var wire 1 ! y $end
$var reg 1 " a $end
$var reg 1 # b $end
$var reg 1 $ sel $end
$scope module uut $end
$var wire 1 " a $end
$var wire 1 # b $end
$var wire 1 $ sel $end
$var wire 1 ! y $end
$upscope $end
$upscope $end
$enddefinitions $end
$comment Show the parameter values. $end
$dumpall
$end
#0
$dumpvars
0$
0#
0"
0!
$end
#10000
1!
1#
#20000
0!
0#
1"
#30000
1!
1#
#40000
0!
1$
0#
0"
#50000
1#
#60000
1!
0#
1"
#70000
1#
