003_Sequential_Circuits/002_JK_Latch/jk_latch.v
module jk_latch(
    input j,
    input k,
    output reg q,
    output qn
);

assign qn = ~q;

always @(j or k) begin
    case ({j,k})
        2'b00: q = q;     // Hold
        2'b01: q = 1'b0;  // Reset
        2'b10: q = 1'b1;  // Set
        2'b11: q = ~q;    // Toggle
    endcase
end

endmodule

003_Sequential_Circuits/002_JK_Latch/jk_latch_tb.v
module jk_latch_tb;
wire q,qn;
reg j,k;
jk_latch uut(
.j(j),
.k(k),
.q(q),
.qn(qn)
);
initial begin
$dumpfile("jk_latch.vcd");
$dumpvars(0,jk_latch_tb);
j=0;k=0;#10;
j=0;k=1;#10;
j=0;k=0;#10;
j=1;k=0;#10;
j=0;k=0;#10;
j=1;k=1;#10;
j=0;k=0;#10;
j=1;k=1;#10;
$finish;
end
endmodule

003_Sequential_Circuits/002_JK_Latch/jk_latch.vcd
$date
	Tue Jun 16 09:51:14 2026
$end
$version
	Icarus Verilog
$end
$timescale
	1s
$end
$scope module jk_latch_tb $end
$var wire 1 ! qn $end
$var wire 1 " q $end
$var reg 1 # j $end
$var reg 1 $ k $end
$scope module uut $end
$var wire 1 # j $end
$var wire 1 $ k $end
$var wire 1 ! qn $end
$var reg 1 " q $end
$upscope $end
$upscope $end
$enddefinitions $end
$comment Show the parameter values. $end
$dumpall
$end
#0
$dumpvars
0$
0#
x"
x!
$end
#10
1!
0"
1$
#20
0$
#30
0!
1"
1#
#40
0#
#50
1!
0"
1$
1#
#60
0$
0#
#70
0!
1"
1$
1#
