003_Sequential_Circuits/008_t_flip_flop/t_flipflop.v
module t_ff(input t,clk,output reg q,output qn);
assign qn = ~q;
always @(posedge clk)begin
case(t)
1'b0:q=1'b1;
1'b1:q=1'b0;
endcase
end
endmodule

003_Sequential_Circuits/008_t_flip_flop/t_flipflop_tb.v
module t_ff_tb;
wire q,qn;
reg t,clk;
t_ff uut(
.t(t),
.clk(clk),
.q(q),
.qn(qn)
);
always #5 clk = ~clk;
initial begin
$dumpfile("t_flipflop.vcd");
$dumpvars(0,t_ff_tb);
clk=0;
t=0;#10;
t=1;#10;
t=0;#10;
t=1;#10;
$finish;
end
endmodule

003_Sequential_Circuits/008_t_flip_flop/t_flipflop.vcd
$date
	Tue Jun 16 23:30:12 2026
$end
$version
	Icarus Verilog
$end
$timescale
	1s
$end
$scope module t_ff_tb $end
$var wire 1 ! qn $end
$var wire 1 " q $end
$var reg 1 # clk $end
$var reg 1 $ t $end
$scope module uut $end
$var wire 1 # clk $end
$var wire 1 ! qn $end
$var wire 1 $ t $end
$var reg 1 " q $end
$upscope $end
$upscope $end
$enddefinitions $end
$comment Show the parameter values. $end
$dumpall
$end
#0
$dumpvars
0$
0#
x"
x!
$end
#5
0!
1"
1#
#10
0#
1$
#15
1!
0"
1#
#20
0#
0$
#25
0!
1"
1#
#30
0#
1$
#35
1!
0"
1#
