002_Combinational_Circuits/009_Comparartor_2bit/comparartor_2bit.v
module comparator_2bit(
    input [1:0] A,
    input [1:0] B,
    output A_gt_B,
    output A_eq_B,
    output A_lt_B
);

assign A_gt_B = (A > B);
assign A_eq_B = (A == B);
assign A_lt_B = (A < B);

endmodule

002_Combinational_Circuits/009_Comparartor_2bit/comparartor_2bit_tb.v
`timescale 1ns/1ps

module comparator_2bit_tb;

reg [1:0] A, B;
wire A_gt_B, A_eq_B, A_lt_B;

comparator_2bit uut (
    .A(A),
    .B(B),
    .A_gt_B(A_gt_B),
    .A_eq_B(A_eq_B),
    .A_lt_B(A_lt_B)
);

initial begin
    $dumpfile("comparator_2bit.vcd");
    $dumpvars(0, comparator_2bit_tb);

    A=2'b00; B=2'b00; #10;
    A=2'b00; B=2'b01; #10;
    A=2'b00; B=2'b10; #10;
    A=2'b00; B=2'b11; #10;

    A=2'b01; B=2'b00; #10;
    A=2'b01; B=2'b01; #10;
    A=2'b01; B=2'b10; #10;
    A=2'b01; B=2'b11; #10;

    A=2'b10; B=2'b00; #10;
    A=2'b10; B=2'b01; #10;
    A=2'b10; B=2'b10; #10;
    A=2'b10; B=2'b11; #10;

    A=2'b11; B=2'b00; #10;
    A=2'b11; B=2'b01; #10;
    A=2'b11; B=2'b10; #10;
    A=2'b11; B=2'b11; #10;

    $finish;
end

endmodule

002_Combinational_Circuits/009_Comparartor_2bit/comparator_2bit.vcd
$date
	Tue Jun  9 11:08:39 2026
$end
$version
	Icarus Verilog
$end
$timescale
	1ps
$end
$scope module comparator_2bit_tb $end
$var wire 1 ! A_lt_B $end
$var wire 1 " A_gt_B $end
$var wire 1 # A_eq_B $end
$var reg 2 $ A [1:0] $end
$var reg 2 % B [1:0] $end
$scope module uut $end
$var wire 2 & A [1:0] $end
$var wire 2 ' B [1:0] $end
$var wire 1 ! A_lt_B $end
$var wire 1 " A_gt_B $end
$var wire 1 # A_eq_B $end
$upscope $end
$upscope $end
$enddefinitions $end
$comment Show the parameter values. $end
$dumpall
$end
#0
$dumpvars
b0 '
b0 &
b0 %
b0 $
1#
0"
0!
$end
#10000
0#
1!
b1 %
b1 '
#20000
b10 %
b10 '
#30000
b11 %
b11 '
#40000
1"
0!
b0 %
b0 '
b1 $
b1 &
#50000
0"
1#
b1 %
b1 '
#60000
0#
1!
b10 %
b10 '
#70000
b11 %
b11 '
#80000
1"
0!
b0 %
b0 '
b10 $
b10 &
#90000
b1 %
b1 '
#100000
0"
1#
b10 %
b10 '
#110000
0#
1!
b11 %
b11 '
#120000
1"
b0 %
b0 '
0#
0!
b11 $
b11 &
#130000
b1 %
b1 '
#140000
b10 %
b10 '
#150000
0"
1#
b11 %
b11 '
