002_Combinational_Circuits/013_Demux_4to1/demux_4to1.v
module demux_1to4(
    input D,
    input [1:0] sel,
    output Y0, Y1, Y2, Y3
);

assign Y0 = D & ~sel[1] & ~sel[0];
assign Y1 = D & ~sel[1] &  sel[0];
assign Y2 = D &  sel[1] & ~sel[0];
assign Y3 = D &  sel[1] &  sel[0];

endmodule

002_Combinational_Circuits/013_Demux_4to1/demux_4to1_tb.v
`timescale 1ns/1ps

module demux_1to4_tb;

reg D;
reg [1:0] sel;
wire Y0, Y1, Y2, Y3;

demux_1to4 uut (
    .D(D),
    .sel(sel),
    .Y0(Y0),
    .Y1(Y1),
    .Y2(Y2),
    .Y3(Y3)
);

initial begin
    $dumpfile("demux_1to4.vcd");
    $dumpvars(0, demux_1to4_tb);

    D = 1;

    sel = 2'b00; #10;
    sel = 2'b01; #10;
    sel = 2'b10; #10;
    sel = 2'b11; #10;

    D = 0;
    sel = 2'b00; #10;
    sel = 2'b01; #10;
    sel = 2'b10; #10;
    sel = 2'b11; #10;

    $finish;
end

endmodule

002_Combinational_Circuits/013_Demux_4to1/demux_1to4.vcd
$date
	Tue Jun  9 12:56:58 2026
$end
$version
	Icarus Verilog
$end
$timescale
	1ps
$end
$scope module demux_1to4_tb $end
$var wire 1 ! Y3 $end
$var wire 1 " Y2 $end
$var wire 1 # Y1 $end
$var wire 1 $ Y0 $end
$var reg 1 % D $end
$var reg 2 & sel [1:0] $end
$scope module uut $end
$var wire 1 % D $end
$var wire 1 $ Y0 $end
$var wire 1 # Y1 $end
$var wire 1 " Y2 $end
$var wire 1 ! Y3 $end
$var wire 2 ' sel [1:0] $end
$upscope $end
$upscope $end
$enddefinitions $end
$comment Show the parameter values. $end
$dumpall
$end
#0
$dumpvars
b0 '
b0 &
1%
1$
0#
0"
0!
$end
#10000
0$
1#
b1 &
b1 '
#20000
0$
1"
0#
b10 &
b10 '
#30000
0"
1!
b11 &
b11 '
#40000
0!
b0 &
b0 '
0%
#50000
b1 &
b1 '
#60000
b10 &
b10 '
#70000
b11 &
b11 '
