002_Combinational_Circuits/014_Demux_8to1/demux_8to1.v
module demux_1to8(
input D,
input [2:0]sel,
output Y7,Y6,Y5,Y4,Y3,Y2,Y1,Y0
);
assign Y0 = D & ~sel[2] & ~sel[1] & ~sel[0];
assign Y1 = D & ~sel[2] & ~sel[1] & sel[0];
assign Y2 = D & ~sel[2] & sel[1] & ~sel[0];
assign Y3 = D & ~sel[2] & sel[1] & sel[0];
assign Y4 = D & sel[2] & ~sel[1] & ~sel[0];
assign Y5 = D & sel[2] & ~sel[1] & sel[0];
assign Y6 = D & sel[2] & sel[1] & ~sel[0];
assign Y7 = D & sel[2] & sel[1] & sel[0];
endmodule

002_Combinational_Circuits/014_Demux_8to1/demux_8to1_tb.v
`timescale 1ns/1ps

module demux_1to8_tb;

reg D;
reg [2:0] sel;
wire Y0, Y1, Y2, Y3, Y4, Y5, Y6, Y7;

demux_1to8 uut (
    .D(D),
    .sel(sel),
    .Y0(Y0), .Y1(Y1), .Y2(Y2), .Y3(Y3),
    .Y4(Y4), .Y5(Y5), .Y6(Y6), .Y7(Y7)
);

initial begin
    $dumpfile("demux_1to8.vcd");
    $dumpvars(0, demux_1to8_tb);
    D = 0;

    sel = 3'b000; #10;
    sel = 3'b001; #10;
    sel = 3'b010; #10;
    sel = 3'b011; #10;
    sel = 3'b100; #10;
    sel = 3'b101; #10;
    sel = 3'b110; #10;
    sel = 3'b111; #10;



    D = 1;

    sel = 3'b000; #10;
    sel = 3'b001; #10;
    sel = 3'b010; #10;
    sel = 3'b011; #10;
    sel = 3'b100; #10;
    sel = 3'b101; #10;
    sel = 3'b110; #10;
    sel = 3'b111; #10;

    $finish;
end

endmodule

002_Combinational_Circuits/014_Demux_8to1/demux_1to8.vcd
$date
	Tue Jun  9 13:13:08 2026
$end
$version
	Icarus Verilog
$end
$timescale
	1ps
$end
$scope module demux_1to8_tb $end
$var wire 1 ! Y7 $end
$var wire 1 " Y6 $end
$var wire 1 # Y5 $end
$var wire 1 $ Y4 $end
$var wire 1 % Y3 $end
$var wire 1 & Y2 $end
$var wire 1 ' Y1 $end
$var wire 1 ( Y0 $end
$var reg 1 ) D $end
$var reg 3 * sel [2:0] $end
$scope module uut $end
$var wire 1 ) D $end
$var wire 1 ( Y0 $end
$var wire 1 ' Y1 $end
$var wire 1 & Y2 $end
$var wire 1 % Y3 $end
$var wire 1 $ Y4 $end
$var wire 1 # Y5 $end
$var wire 1 " Y6 $end
$var wire 1 ! Y7 $end
$var wire 3 + sel [2:0] $end
$upscope $end
$upscope $end
$enddefinitions $end
$comment Show the parameter values. $end
$dumpall
$end
#0
$dumpvars
b0 +
b0 *
0)
0(
0'
0&
0%
0$
0#
0"
0!
$end
#10000
b1 *
b1 +
#20000
b10 *
b10 +
#30000
b11 *
b11 +
#40000
b100 *
b100 +
#50000
b101 *
b101 +
#60000
b110 *
b110 +
#70000
b111 *
b111 +
#80000
1(
b0 *
b0 +
1)
#90000
0(
1'
b1 *
b1 +
#100000
0(
1&
0'
b10 *
b10 +
#110000
0&
1%
b11 *
b11 +
#120000
0(
1$
0%
b100 *
b100 +
#130000
0$
1#
b101 *
b101 +
#140000
0$
1"
0#
b110 *
b110 +
#150000
0"
1!
b111 *
b111 +
