002_Combinational_Circuits/002_Full_Adder/full_adder.v
module full_adder(input a,b,c,output s,co);
assign s = a^b^c;
assign co = a&b | b&c | c&a;
endmodule

002_Combinational_Circuits/002_Full_Adder/full_adder_tb.v
module full_adder_tb;
reg a,b,c;
wire s,co;
full_adder uut(
.a(a),
.b(b),
.c(c),
.s(s),
.co(co)
);
initial begin
$dumpfile("full_adder.vcd");
$dumpvars(0,full_adder_tb);
a=0;b=0;c=0;#10;
a=0;b=0;c=1;#10;
a=0;b=1;c=0;#10;
a=0;b=1;c=1;#10;
a=1;b=0;c=0;#10;
a=1;b=0;c=1;#10;
a=1;b=1;c=0;#10;
a=1;b=1;c=1;#10;
$finish;
end
endmodule

002_Combinational_Circuits/002_Full_Adder/full_adder.vcd
$date
	Fri Jun  5 16:53:56 2026
$end
$version
	Icarus Verilog
$end
$timescale
	1s
$end
$scope module full_adder_tb $end
$var wire 1 ! s $end
$var wire 1 " co $end
$var reg 1 # a $end
$var reg 1 $ b $end
$var reg 1 % c $end
$scope module uut $end
$var wire 1 # a $end
$var wire 1 $ b $end
$var wire 1 % c $end
$var wire 1 " co $end
$var wire 1 ! s $end
$upscope $end
$upscope $end
$enddefinitions $end
$comment Show the parameter values. $end
$dumpall
$end
#0
$dumpvars
0%
0$
0#
0"
0!
$end
#10
1!
1%
#20
0%
1$
#30
1"
0!
1%
#40
0"
1!
0%
0$
1#
#50
1"
0!
1%
#60
0%
1$
#70
1!
1%
