003_Sequential_Circuits/007_d_flip_flop/d_flipflop.v
module d_ff(input d,clk,output reg q,output qn);
assign qn = ~q;
always @(posedge clk)begin
case(d)
1'b0:q=1'b0;
1'b1:q=1'b1;
endcase
end
endmodule

003_Sequential_Circuits/007_d_flip_flop/d_flipflop_tb.v
module d_ff_tb;
wire q,qn;
reg d,clk;
d_ff uut(
.d(d),
.clk(clk),
.q(q),
.qn(qn)
);
always #5 clk = ~clk;
initial begin
$dumpfile("d_flipflop.vcd");
$dumpvars(0,d_ff_tb);
clk=0;
d=0;#10;
d=1;#10;
d=0;#10;
d=1;#10;
$finish;
end
endmodule

003_Sequential_Circuits/007_d_flip_flop/d_flipflop.vcd
$date
	Tue Jun 16 23:26:28 2026
$end
$version
	Icarus Verilog
$end
$timescale
	1s
$end
$scope module d_ff_tb $end
$var wire 1 ! qn $end
$var wire 1 " q $end
$var reg 1 # clk $end
$var reg 1 $ d $end
$scope module uut $end
$var wire 1 # clk $end
$var wire 1 $ d $end
$var wire 1 ! qn $end
$var reg 1 " q $end
$upscope $end
$upscope $end
$enddefinitions $end
$comment Show the parameter values. $end
$dumpall
$end
#0
$dumpvars
0$
0#
x"
x!
$end
#5
1!
0"
1#
#10
0#
1$
#15
0!
1"
1#
#20
0#
0$
#25
1!
0"
1#
#30
0#
1$
#35
0!
1"
1#
